nearest_neighbor_acoustic_interpolation-0.1.2.dist-info/METADATA
nearest_neighbor_acoustic_interpolation-0.1.2.dist-info/WHEEL
nearest_neighbor_acoustic_interpolation-0.1.2.dist-info/entry_points.txt
nearest_neighbor_acoustic_interpolation/NearestNeighborBilinearAverageModel.py
nearest_neighbor_acoustic_interpolation/__init__.py
nearest_neighbor_acoustic_interpolation-0.1.2.dist-info/RECORD
