Metadata-Version: 2.1
Name: nearest_neighbor_acoustic_interpolation
Version: 0.1.2
Summary: This is the code behind the paper 'Translating jet noise measurement to near-field level maps with nearest neighbor bilinear smoothing interpolation'
Keywords: interpolation,acoustic
Author-Email: frankmobley <mobssoft@gmail.com>, "Dr. Frank Mobley" <frank.mobley.1@afrl.af.mil>
License: MIT
Project-URL: Homepage, https://gitlab.com/acousticprocessing/nearest-neighbor-interpolation
Requires-Python: >=3.9
Requires-Dist: numpy>=1.21.5
Requires-Dist: pandas>=1.4.3
Requires-Dist: scipy>=1.9.1
